truenas_backup_tool/__init__.py
truenas_backup_tool/__main__.py
truenas_backup_tool/cli.py
truenas_backup_tool-0.1.1.dist-info/licenses/LICENSE
truenas_backup_tool-0.1.1.dist-info/METADATA
truenas_backup_tool-0.1.1.dist-info/WHEEL
truenas_backup_tool-0.1.1.dist-info/entry_points.txt
truenas_backup_tool-0.1.1.dist-info/top_level.txt
truenas_backup_tool-0.1.1.dist-info/RECORD
