Metadata-Version: 2.4
Name: truenas_backup_tool
Version: 0.1.1
Summary: A simple tool to fetch backups from the TrueNAS via the JSON-RPC protocol
Author-email: Stanislav Meduna <stano@meduna.org>
Project-URL: Homepage, https://github.com/numo68/truenas-backup
Project-URL: Bug Tracker, https://github.com/numo68/truenas-backup/issues
Classifier: Programming Language :: Python :: 3
Classifier: License :: OSI Approved :: MIT License
Classifier: Operating System :: OS Independent
Requires-Python: >=3.10
License-File: LICENSE
Requires-Dist: PyYAML
Requires-Dist: schema
Requires-Dist: prometheus-client
Requires-Dist: PyCryptodome
Requires-Dist: httpx
Dynamic: license-file
